vassal/__init__.py
vassal/scheduler.py
vassal/ssh.py
vassal/terminal.py
vassal-0.0.2.dist-info/LICENSE
vassal-0.0.2.dist-info/METADATA
vassal-0.0.2.dist-info/WHEEL
vassal-0.0.2.dist-info/top_level.txt
vassal-0.0.2.dist-info/RECORD
