Metadata-Version: 2.1
Name: vassal
Version: 0.0.2
Summary: The automate terminal
Home-page: https://github.com/Shawn-Shan/vassal
Author: Shawn Shan
Author-email: shawnshan1825@gmail.com
License: UNKNOWN
Platform: UNKNOWN
Classifier: Programming Language :: Python :: 3
Classifier: License :: OSI Approved :: MIT License
Classifier: Operating System :: OS Independent
Requires-Dist: scp (>=0.13.0)
Requires-Dist: cryptography (>=2.4.1)
Requires-Dist: paramiko (>=2.4.2)
